{
  "$schema": "../../../node_modules/@microsoft/sp-module-interfaces/lib/manifestSchemas/jsonSchemas/clientSideComponentManifestSchema.json",

  "id": "70ab5d0c-f735-4842-8a3e-5976a49d4d8f",
  "componentType": "WebPart",
  "version": "0.0.1",
  "manifestVersion": 2,

  "preconfiguredEntries": [{
    "groupId": "70ab5d0c-f735-4842-8a3e-5976a49d4d8f",
    "group": { "default": "Under Development" },
    "title": { "default": "DocumentCardExample" },
    "description": { "default": "DocumentCardExample description" },
    "officeFabricIconFontName": "Page",
    "properties": {
      "description": "DocumentCardExample"
    }
  }]
}
